rebuff/__init__.py
rebuff/_version.py
rebuff/detect_pi_heuristics.py
rebuff/detect_pi_openai.py
rebuff/detect_pi_vectorbase.py
rebuff/rebuff.py
rebuff/sdk.py
rebuff-0.1.1.dist-info/METADATA
rebuff-0.1.1.dist-info/WHEEL
rebuff-0.1.1.dist-info/RECORD
