Metadata-Version: 2.1
Name: rebuff
Version: 0.1.1
Summary: Rebuff is designed to protect AI applications from prompt injection (PI) attacks through a multi-layered defense.
License: Apache-2.0
Author: ProtectAI
Author-email: community@protectai.com
Requires-Python: >=3.8.1,<3.13
Classifier: License :: OSI Approved :: Apache Software License
Classifier: Programming Language :: Python :: 3
Classifier: Programming Language :: Python :: 3.9
Classifier: Programming Language :: Python :: 3.10
Classifier: Programming Language :: Python :: 3.11
Classifier: Programming Language :: Python :: 3.12
Requires-Dist: langchain (>=0.1.1,<0.2.0)
Requires-Dist: langchain-openai (>=0.0.3,<0.0.4)
Requires-Dist: openai (>=1.8.0,<2.0.0)
Requires-Dist: pinecone-client (>=3.0.0,<4.0.0)
Requires-Dist: pydantic (>=2.5.3,<3.0.0)
Requires-Dist: requests (>=2.31.0,<3.0.0)
Requires-Dist: tiktoken (>=0.5.2,<0.6.0)
